report2junit/__init__.py
report2junit/junit.py
report2junit/reports/__init__.py
report2junit/reports/cfn_guard.py
report2junit/reports/cfn_nag.py
report2junit/reports/junit.py
report2junit/reports/noreport.py
report2junit/reports/report_factory.py
report2junit-0.3.2.dist-info/LICENSE.md
report2junit-0.3.2.dist-info/METADATA
report2junit-0.3.2.dist-info/WHEEL
report2junit-0.3.2.dist-info/entry_points.txt
report2junit-0.3.2.dist-info/RECORD
