Metadata-Version: 2.1
Name: report2junit
Version: 0.3.2
Summary: `report2junit` is a tool that converts various reports into the JUnit format.
License: MIT
Author: Joris Conijn
Author-email: joris@conijnonline.nl
Requires-Python: >=3.8,<4.0
Classifier: License :: OSI Approved :: MIT License
Classifier: Programming Language :: Python :: 3
Classifier: Programming Language :: Python :: 3.8
Classifier: Programming Language :: Python :: 3.9
Classifier: Programming Language :: Python :: 3.10
Classifier: Programming Language :: Python :: 3.11
Requires-Dist: click (>=8.0.3,<9.0.0)
Requires-Dist: junit-xml (>=1.9,<2.0)
